ilgen/__init__.py
ilgen/main.py
ilgen-0.1.1.dist-info/METADATA
ilgen-0.1.1.dist-info/WHEEL
ilgen-0.1.1.dist-info/entry_points.txt
ilgen-0.1.1.dist-info/licenses/LICENSE
ilgen-0.1.1.dist-info/RECORD
