Metadata-Version: 2.4
Name: ilgen
Version: 0.1.1
Summary: Helps managing your project's instance list
Project-URL: Homepage, https://git.private.coffee/privatecoffee/ilgen
Project-URL: Bug Tracker, https://git.private.coffee/privatecoffee/ilgen/issues
Project-URL: Source Code, https://git.private.coffee/privatecoffee/ilgen
Author-email: "Private.coffee Team" <support@private.coffee>
License: Copyright (c) 2025 Private.coffee <support@private.coffee>
License-File: LICENSE
Classifier: License :: OSI Approved :: MIT License
Classifier: Operating System :: OS Independent
Classifier: Programming Language :: Python :: 3
Requires-Python: >=3.8
Requires-Dist: pycountry
